pydantic_geojson/__init__.py
pydantic_geojson/_base.py
pydantic_geojson/feature.py
pydantic_geojson/feature_collection.py
pydantic_geojson/geometry_collection.py
pydantic_geojson/line_string.py
pydantic_geojson/multi_line_string.py
pydantic_geojson/multi_point.py
pydantic_geojson/multi_polygon.py
pydantic_geojson/object_type.py
pydantic_geojson/point.py
pydantic_geojson/polygon.py
pydantic_geojson/py.typed
pydantic_geojson-0.3.1.dist-info/METADATA
pydantic_geojson-0.3.1.dist-info/WHEEL
pydantic_geojson-0.3.1.dist-info/licenses/AUTHORS
pydantic_geojson-0.3.1.dist-info/licenses/LICENSE
pydantic_geojson-0.3.1.dist-info/RECORD
