Metadata-Version: 2.4
Name: pydantic_geojson
Version: 0.3.1
Summary: Pydantic validation for GeoJson
License: MIT
License-File: AUTHORS
License-File: LICENSE
Keywords: pydantic,validation,geojson,schema,gis,geo,json,json-schema,rest,fastapi,swagger,openapi
Author: Aliaksandr Vaskevich
Author-email: vaskevic.an@gmail.com
Requires-Python: >=3.9,<4.0
Classifier: Intended Audience :: Developers
Classifier: License :: OSI Approved :: MIT License
Classifier: Programming Language :: Python :: 3
Classifier: Programming Language :: Python :: 3.9
Classifier: Programming Language :: Python :: 3.10
Classifier: Programming Language :: Python :: 3.11
Classifier: Programming Language :: Python :: 3.12
Classifier: Programming Language :: Python :: 3.13
Classifier: Programming Language :: Python :: 3.14
Classifier: Programming Language :: Python :: Implementation :: CPython
Classifier: Topic :: Scientific/Engineering :: GIS
Requires-Dist: pydantic (>=1.9,<3.0)
Project-URL: Documentation, https://github.com/gb-libs/pydantic-geojson
Project-URL: Homepage, https://github.com/gb-libs/pydantic-geojson
Project-URL: Repository, https://github.com/gb-libs/pydantic-geojson
